pybberlink/__init__.py
pybberlink/main.py
pybberlink-0.1.1.dist-info/METADATA
pybberlink-0.1.1.dist-info/WHEEL
pybberlink-0.1.1.dist-info/entry_points.txt
pybberlink-0.1.1.dist-info/top_level.txt
pybberlink-0.1.1.dist-info/RECORD
