Metadata-Version: 2.2
Name: pybberlink
Version: 0.1.1
Summary: A package to encode and decode text using the Gibberlink protocol.
Author-email: Mads Henrichsen <mads@syv.ai>
Classifier: Programming Language :: Python :: 3
Classifier: Operating System :: OS Independent
Requires-Python: >=3.6
Requires-Dist: numpy
Requires-Dist: reedsolo
